README.rst
setup.py
./__init__.py
./activity_stream.py
./activity_stream.xml
./tryton.cfg
./tests/__init__.py
./tests/test_activity_stream.py
trytond_nereid_activity_stream.egg-info/PKG-INFO
trytond_nereid_activity_stream.egg-info/SOURCES.txt
trytond_nereid_activity_stream.egg-info/dependency_links.txt
trytond_nereid_activity_stream.egg-info/entry_points.txt
trytond_nereid_activity_stream.egg-info/not-zip-safe
trytond_nereid_activity_stream.egg-info/requires.txt
trytond_nereid_activity_stream.egg-info/top_level.txt