Metadata-Version: 1.1
Name: trytond-nereid-activity-stream
Version: 3.0.2.1
Summary: Activity Stream (a.k.a news feed) for Tryton nereid
Home-page: https://github.com/openlabs/nereid-activity-stream
Author: Openlabs Technologies & consulting (P) Limited
Author-email: info@openlabs.co.in
License: GPLv3
Platform: UNKNOWN
Classifier: Development Status :: 4 - Beta
Classifier: Environment :: Plugins
Classifier: Intended Audience :: Developers
Classifier: License :: OSI Approved :: GNU General Public License v3 (GPLv3)
Classifier: Natural Language :: English
Classifier: Operating System :: OS Independent
Classifier: Programming Language :: Python
Classifier: Framework :: Tryton
Classifier: Topic :: Office/Business
